{
  "schema_version": "1.0",
  "artifact_type": "trend_registry",
  "run_id": "run_20260430_145929",
  "generated_at": "2026-04-30T14:59:32",
  "history_window": {
    "run_count": 2
  },
  "analyzers": [
    {
      "analyzer_id": "GA01",
      "history": [
        {
          "run_id": "run_20260430_145357",
          "start_time": "2026-04-30T14:54:00",
          "coverage_ratio": 1.0,
          "usable_frame_ratio": 1.0,
          "reference_quality_score": 0.5
        },
        {
          "run_id": "run_20260430_145929",
          "start_time": "2026-04-30T14:59:32",
          "coverage_ratio": 1.0,
          "usable_frame_ratio": 1.0,
          "reference_quality_score": 0.5,
          "sample_count": 128
        }
      ],
      "drift_indicator": "stable",
      "spc_metric": {
        "metric": "usable_frame_ratio",
        "center_line": 1.0,
        "ucl": 1.0,
        "lcl": 1.0,
        "latest": 1.0
      },
      "control_limit_status": "in_control",
      "reference_quality_trend": "stable",
      "coverage_trend": "stable"
    },
    {
      "analyzer_id": "GA02",
      "history": [
        {
          "run_id": "run_20260430_145357",
          "start_time": "2026-04-30T14:54:00",
          "coverage_ratio": 1.0,
          "usable_frame_ratio": 1.0,
          "reference_quality_score": 0.5
        },
        {
          "run_id": "run_20260430_145929",
          "start_time": "2026-04-30T14:59:32",
          "coverage_ratio": 1.0,
          "usable_frame_ratio": 1.0,
          "reference_quality_score": 0.5,
          "sample_count": 128
        }
      ],
      "drift_indicator": "stable",
      "spc_metric": {
        "metric": "usable_frame_ratio",
        "center_line": 1.0,
        "ucl": 1.0,
        "lcl": 1.0,
        "latest": 1.0
      },
      "control_limit_status": "in_control",
      "reference_quality_trend": "stable",
      "coverage_trend": "stable"
    },
    {
      "analyzer_id": "GA03",
      "history": [
        {
          "run_id": "run_20260430_145357",
          "start_time": "2026-04-30T14:54:00",
          "coverage_ratio": 1.0,
          "usable_frame_ratio": 1.0,
          "reference_quality_score": 0.5
        },
        {
          "run_id": "run_20260430_145929",
          "start_time": "2026-04-30T14:59:32",
          "coverage_ratio": 1.0,
          "usable_frame_ratio": 1.0,
          "reference_quality_score": 0.5,
          "sample_count": 128
        }
      ],
      "drift_indicator": "stable",
      "spc_metric": {
        "metric": "usable_frame_ratio",
        "center_line": 1.0,
        "ucl": 1.0,
        "lcl": 1.0,
        "latest": 1.0
      },
      "control_limit_status": "in_control",
      "reference_quality_trend": "stable",
      "coverage_trend": "stable"
    },
    {
      "analyzer_id": "GA04",
      "history": [
        {
          "run_id": "run_20260430_145357",
          "start_time": "2026-04-30T14:54:00",
          "coverage_ratio": 1.0,
          "usable_frame_ratio": 1.0,
          "reference_quality_score": 0.5
        },
        {
          "run_id": "run_20260430_145929",
          "start_time": "2026-04-30T14:59:32",
          "coverage_ratio": 1.0,
          "usable_frame_ratio": 1.0,
          "reference_quality_score": 0.5,
          "sample_count": 128
        }
      ],
      "drift_indicator": "stable",
      "spc_metric": {
        "metric": "usable_frame_ratio",
        "center_line": 1.0,
        "ucl": 1.0,
        "lcl": 1.0,
        "latest": 1.0
      },
      "control_limit_status": "in_control",
      "reference_quality_trend": "stable",
      "coverage_trend": "stable"
    },
    {
      "analyzer_id": "GA05",
      "history": [
        {
          "run_id": "run_20260430_145357",
          "start_time": "2026-04-30T14:54:00",
          "coverage_ratio": 1.0,
          "usable_frame_ratio": 1.0,
          "reference_quality_score": 0.5
        },
        {
          "run_id": "run_20260430_145929",
          "start_time": "2026-04-30T14:59:32",
          "coverage_ratio": 1.0,
          "usable_frame_ratio": 1.0,
          "reference_quality_score": 0.5,
          "sample_count": 128
        }
      ],
      "drift_indicator": "stable",
      "spc_metric": {
        "metric": "usable_frame_ratio",
        "center_line": 1.0,
        "ucl": 1.0,
        "lcl": 1.0,
        "latest": 1.0
      },
      "control_limit_status": "in_control",
      "reference_quality_trend": "stable",
      "coverage_trend": "stable"
    },
    {
      "analyzer_id": "GA06",
      "history": [
        {
          "run_id": "run_20260430_145357",
          "start_time": "2026-04-30T14:54:00",
          "coverage_ratio": 1.0,
          "usable_frame_ratio": 1.0,
          "reference_quality_score": 0.5
        },
        {
          "run_id": "run_20260430_145929",
          "start_time": "2026-04-30T14:59:32",
          "coverage_ratio": 1.0,
          "usable_frame_ratio": 1.0,
          "reference_quality_score": 0.5,
          "sample_count": 128
        }
      ],
      "drift_indicator": "stable",
      "spc_metric": {
        "metric": "usable_frame_ratio",
        "center_line": 1.0,
        "ucl": 1.0,
        "lcl": 1.0,
        "latest": 1.0
      },
      "control_limit_status": "in_control",
      "reference_quality_trend": "stable",
      "coverage_trend": "stable"
    },
    {
      "analyzer_id": "GA07",
      "history": [
        {
          "run_id": "run_20260430_145357",
          "start_time": "2026-04-30T14:54:00",
          "coverage_ratio": 1.0,
          "usable_frame_ratio": 1.0,
          "reference_quality_score": 0.5
        },
        {
          "run_id": "run_20260430_145929",
          "start_time": "2026-04-30T14:59:32",
          "coverage_ratio": 1.0,
          "usable_frame_ratio": 1.0,
          "reference_quality_score": 0.5,
          "sample_count": 128
        }
      ],
      "drift_indicator": "stable",
      "spc_metric": {
        "metric": "usable_frame_ratio",
        "center_line": 1.0,
        "ucl": 1.0,
        "lcl": 1.0,
        "latest": 1.0
      },
      "control_limit_status": "in_control",
      "reference_quality_trend": "stable",
      "coverage_trend": "stable"
    },
    {
      "analyzer_id": "GA08",
      "history": [
        {
          "run_id": "run_20260430_145357",
          "start_time": "2026-04-30T14:54:00",
          "coverage_ratio": 1.0,
          "usable_frame_ratio": 1.0,
          "reference_quality_score": 0.5
        },
        {
          "run_id": "run_20260430_145929",
          "start_time": "2026-04-30T14:59:32",
          "coverage_ratio": 1.0,
          "usable_frame_ratio": 1.0,
          "reference_quality_score": 0.5,
          "sample_count": 128
        }
      ],
      "drift_indicator": "stable",
      "spc_metric": {
        "metric": "usable_frame_ratio",
        "center_line": 1.0,
        "ucl": 1.0,
        "lcl": 1.0,
        "latest": 1.0
      },
      "control_limit_status": "in_control",
      "reference_quality_trend": "stable",
      "coverage_trend": "stable"
    }
  ],
  "route_temp_source_groups": [
    {
      "route": "co2",
      "temperature_c": 20.0,
      "source": "co2:1000",
      "history": [
        {
          "run_id": "run_20260430_145929",
          "start_time": "2026-04-30T14:59:32",
          "usable_frame_ratio": 1.0,
          "reference_quality_score": 0.0
        }
      ],
      "drift_indicator": "stable",
      "spc_metric": {
        "metric": "usable_frame_ratio",
        "center_line": 1.0,
        "ucl": 1.0,
        "lcl": 1.0,
        "latest": 1.0
      },
      "control_limit_status": "in_control",
      "reference_quality_trend": "stable",
      "coverage_trend": "stable"
    },
    {
      "route": "co2",
      "temperature_c": 20.0,
      "source": "co2:400",
      "history": [
        {
          "run_id": "run_20260430_145929",
          "start_time": "2026-04-30T14:59:32",
          "usable_frame_ratio": 1.0,
          "reference_quality_score": 0.0
        }
      ],
      "drift_indicator": "stable",
      "spc_metric": {
        "metric": "usable_frame_ratio",
        "center_line": 1.0,
        "ucl": 1.0,
        "lcl": 1.0,
        "latest": 1.0
      },
      "control_limit_status": "in_control",
      "reference_quality_trend": "stable",
      "coverage_trend": "stable"
    }
  ]
}
